Mathconvert/__init__.py
Mathconvert/mathconvert.py
mathconvert-1.0.0.dist-info/METADATA
mathconvert-1.0.0.dist-info/WHEEL
mathconvert-1.0.0.dist-info/top_level.txt
mathconvert-1.0.0.dist-info/RECORD
